{
  "pdf_path": "D:\\道\\道生一\\一生二\\学习复习\\雨课堂PDF\\环境毒理学-2026春-090963-001-森巴提·叶尔肯\\004-3环境毒理学 第三章-第二章 污染物在环境中的迁移和转化.pdf",
  "pdf_name": "004-3环境毒理学 第三章-第二章 污染物在环境中的迁移和转化.pdf",
  "lesson_seq": 4,
  "lesson_title": "3环境毒理学 第三章",
  "presentation_title": "第二章 污染物在环境中的迁移和转化",
  "chapter_num": 2,
  "chapter_raw": "第二章",
  "page_count": 35,
  "pages": [
    {
      "index": 1,
      "image": "page_001.jpg",
      "embedded_text": null,
      "ocr_text": "环境毒理学\n授课人：森巴提?叶尔肯",
      "ocr_lines_count": 4,
      "ocr_score": 0.98
    },
    {
      "index": 2,
      "image": "page_002.jpg",
      "embedded_text": null,
      "ocr_text": "第二章污染物在环境中的迁移和转化\n本章将讨论以下内容：\n2.1概述\n2.2环境污染物的迁移\n2.3环境污染物的转化",
      "ocr_lines_count": 7,
      "ocr_score": 0.992
    },
    {
      "index": 3,
      "image": "page_003.jpg",
      "embedded_text": null,
      "ocr_text": "2.1概述\n当污染物进入环境介质后，会在多种因素的作用下在环境中\n不断迁移、转化。污染物在环境中发生的各种变化过程称为污\n染物的迁移和转化。\n环境条件\n迁移 转化\n物质基础\n新的、具有理化特征的",
      "ocr_lines_count": 11,
      "ocr_score": 0.989
    },
    {
      "index": 4,
      "image": "page_004.jpg",
      "embedded_text": null,
      "ocr_text": "2.1概述\n例如汞，当汞通过各种途径进入环境后，它不但在水体、大\n气中扩散，而且它存在的形态也会不断发生变化，在不同的\n因素作用下中形成Hg+、甲基汞和二甲基汞等形态。\n大气 水体\n漂浮\n沉降\n农药\n随雨水部分落入\n小部分\n大部分\n作物\n世界环境 土壤\n风和洋流 食物链\nDDT 极地 企鹅\n水生生物的携带 饮水\n意义：研究污染物在环境中的迁移和转化对于阐明人类\n或其他生物在环境中接触污染物的真实情况，有效地防治环\n境污染，保护生态环境，保障人类健康都是很有必要的。",
      "ocr_lines_count": 27,
      "ocr_score": 0.988
    },
    {
      "index": 5,
      "image": "page_005.jpg",
      "embedded_text": null,
      "ocr_text": "2.2环境污染物的迁移\n污染物的迁移 (transportofpollutants)就\n是指污染物在环境中发生的空间位置的相对改变的\n过程。\n气的机械性迁移作用\n水的机械性迁移作用\n机械性迁移\n迁移方式 物理化学性迁移\n重力的机械性迁移作用\n生物性迁移",
      "ocr_lines_count": 14,
      "ocr_score": 0.988
    },
    {
      "index": 6,
      "image": "page_006.jpg",
      "embedded_text": null,
      "ocr_text": "2.2环境污染物的迁移\n（一）气的机械性迁移作用\n扩散+气流搬运\n1．扩散迁移\n大气圈按垂直分布可分为五层：对流层、平流层、中间\n层、暖层和散逸层。不同层次对污染物的扩散作用不同。\n大气重直分层 483KM 散逸层\n(1)风力扩散\n棋具\n(2)气流扩散\n中间层\n(3)湍流扩散\n臭氧层 平流层\n对流层",
      "ocr_lines_count": 22,
      "ocr_score": 0.965
    },
    {
      "index": 7,
      "image": "page_007.jpg",
      "embedded_text": null,
      "ocr_text": "2.2环境污染物的迁移\n影响大气污染物扩散的因素\n正常晴朗大气（下眼上冷） 什么天气会使污染 逆温大气（下冷上暖）\n①大气稳定度 NO. 污染物洁动规小\n在对流层内，气温随海拔高度的增加 PM2.5\nPM10\n而逐渐降低，因此一般情况下，上层空气冷\n而下层暖，下层暖空气有受热膨胀上升的趋\n势，此时大气在垂直方向不稳定，对流显著\n有利于污染物的气流扩散，进而引发风力扩 Z/m 100\n散和湍流扩散逆温现象：上层空气暖而下层\n冷的现象。大气稳定度高，对流作用大为减 稳状态（波浪形\n弱，污染物无法随空气运动扩散秋冬季节中\n国北方的雾霾 .98 中稳状态（锥形）\n②地理地势 0.98\n稳定状态（扇形）\n高耸的山脉会阻滞空气流动，降低风\n速，改变风向。城市中的高层建筑区，如未\n0.98 下层稳定上层不稳定（屋脊形）\n设计合路通道，气流只能在高层建筑间的小 100K\n范围内产生涡流，污染物也无法迅速扩散，\n下层不稳上层稳定（重烟形）\n只能停滞在该地段，引发污染的加剧。",
      "ocr_lines_count": 39,
      "ocr_score": 0.964
    },
    {
      "index": 8,
      "image": "page_008.jpg",
      "embedded_text": null,
      "ocr_text": "2.2环境污染物的迁移\n2.干沉降和湿沉降\n酸化污染物\n湿沉降\n千沉降\n自然来源\n沉降是由于分散相和分散介质的密度不同，分散相粒子在\n力场（重力场或离心力场）作用下发生的定向运动。沉降是\n大气颗粒物主要消除过程之一，按照沉降过程是否需要降水\n冲刷，又可分为干沉降和湿沉降。",
      "ocr_lines_count": 12,
      "ocr_score": 0.962
    },
    {
      "index": 9,
      "image": "page_009.jpg",
      "embedded_text": null,
      "ocr_text": "2.2环境污染物的迁移\n（二）水的机械性迁移作用\n水的机械性迁移作用能够使污染物在不同环境介\n质中发生迁移。\n水流\n降水\n（三）重力的机械迁移作用\n重力的机械迁移作用是指污染物及其搬运载体在\n重力作用下的迁移运动\n除了上述三种机械迁移作用之外，在社会生产和物\n质流通过程中，各种人为的机械搬运污染物的行为已成为\n污染物迁移的重要方式之一。",
      "ocr_lines_count": 14,
      "ocr_score": 0.984
    },
    {
      "index": 10,
      "image": "page_010.jpg",
      "embedded_text": null,
      "ocr_text": "2.2环境污染物的迁移\n二、物理-化学性迁移\n物理-化学性迁移是指元素及其化合物在环境中\n物理化学作用所实现的迁移。\n吸附-解吸、溶解（或絮凝）-沉\n无机化合物 淀、氧化-还原、水解、络合和\n鳌合等作用\n除以上的作用外，还可通过化学\n有机化合物 分解、光化学分解、生化分解和\n聚合作用等",
      "ocr_lines_count": 14,
      "ocr_score": 0.987
    },
    {
      "index": 11,
      "image": "page_011.jpg",
      "embedded_text": null,
      "ocr_text": "2.2环境污染物的迁移\n（一）风化淋溶作用\n环境中的水在重力作用下运动时，可以通过水\n解作用将岩石、矿物中的化学元素溶入到水中的过\n程，称为风化淋溶作用。\n产生\n游离态的元素离子\n疾病的发病率和由于环境中风化淋溶作用所导致的某\n种元素过多或缺乏有着密切联系。",
      "ocr_lines_count": 11,
      "ocr_score": 0.987
    },
    {
      "index": 12,
      "image": "page_012.jpg",
      "embedded_text": null,
      "ocr_text": "2.2环境污染物的迁移\n（二）溶解挥发作用\n大气中的SO2\n溶解作用是一切可溶性污染物污染环 吸收\n境的一种基本方式。例如在大气环境中 降水 烧 燃烧\n生产者 摄入 消费者\n二氧化硫等酸性气体遇到水蒸气就会发 吸收\n动植物遗体、排出物\n生溶解，形成硫酸及亚硫酸，然后在冷\n土壤、水中 火山\n却后形成酸性降水。 分解者 化石\n的SO2 爆发 燃料\n（三）酸碱作用\n环境pH的变化也可以影响污染物的迁移过程。前面提到的酸性降水，\n不仅会造成建筑物的腐蚀和皮肤黏膜的刺激性损伤，而且还会加速环境\n中岩石、矿物风化淋溶的速度。另外，酸性降水还可促使土壤中铝的活\n化。当大量的三价铝进入土壤溶液或河流湖泊等水体，便会对树木与水\n生生物产生毒作用。",
      "ocr_lines_count": 32,
      "ocr_score": 0.979
    },
    {
      "index": 13,
      "image": "page_013.jpg",
      "embedded_text": null,
      "ocr_text": "2.2环境污染物的迁移\n（四）络合作用\n当污染物在环境中迁移时，经常和其他离子、离子\n团或有机大分子络合，而改变污染物的迁移能力和归属\n（五） 吸附作用\n环境中一些物质可以物理或化学吸附某些污染物，\n然后污染物会随之发生迁移。\n氧化-还原作用\nCr20²-+ H20 2Cr02- + 2H+\n还原剂 氧化剂\nCr²++30H-==Cr（OH) OH- CrO2+2H20",
      "ocr_lines_count": 21,
      "ocr_score": 0.968
    },
    {
      "index": 14,
      "image": "page_014.jpg",
      "embedded_text": null,
      "ocr_text": "2.2环境污染物的迁移\n三、生物性迁移\n生物性迁移是指污染物通过生物体的吸附、吸收、\n代谢或死亡等过程发生的迁移。\n生物浓缩\n表现形式 生物积累\n生物放大",
      "ocr_lines_count": 10,
      "ocr_score": 0.985
    },
    {
      "index": 15,
      "image": "page_015.jpg",
      "embedded_text": null,
      "ocr_text": "2.2环境污染物的迁移\n（一）生物浓缩\n生物浓缩是指生物体从环境中蓄积某种污染物，\n从而出现生物体中浓度超出环境中浓度的现象，又被\n称为生物富集。\n生物富集系数（bioconcentrationfactor，BCF）\n生物体内污染物的浓度（mg/kg）\n环境中污染物的浓度（mg/kg)\n阐明污染物在环境中的生物迁移规律，评价和预\n测污染物进入环境后可能产生的危害，以及确定污染\n物的环境容量进而制订环境标准。",
      "ocr_lines_count": 13,
      "ocr_score": 0.986
    },
    {
      "index": 16,
      "image": "page_016.jpg",
      "embedded_text": null,
      "ocr_text": "2.2环境污染物的迁移\n（二）生物积累（bioaccumulation）\n生物积累是指生物个体随着其生长发育的不同阶段\n从环境中蓄积某种污染物，从而使浓缩系数不断增大的\n一种现象。\n生物积累系数（bioaccumulationfactor，BAF）=\n某一生物个体生长发育较后阶段体内蓄积污染物的浓度（mg/kg）\n同一生物个体生长发育较前阶段体内蓄积污染物的浓度（mg/kg）",
      "ocr_lines_count": 10,
      "ocr_score": 0.985
    },
    {
      "index": 17,
      "image": "page_017.jpg",
      "embedded_text": null,
      "ocr_text": "2.2环境污染物的迁移\n生物积累和生物富集的区别\n生物积累：指生物从环境中不断摄取并积累某种物质，使该\n物质在生物体内的浓度随时间增加而增加的过程\n·生物富集：又称生物浓缩，是指生物机体或处于同一营养级\n上的许多生物种群，从周围环境中蓄积某种元素或难分解化\n合物，使生物体内该物质的浓度超过环境中的浓度的现象。\n它强调的是生物体内物质浓度与环境中物质浓度的对比关系",
      "ocr_lines_count": 10,
      "ocr_score": 0.986
    },
    {
      "index": 18,
      "image": "page_018.jpg",
      "embedded_text": null,
      "ocr_text": "2.2环境污染物的迁移\n（三）生物放大\n生物放大是指在生态系统的同一食物链上，生物体\n内某种污染物的浓度随着营养级的提高而逐步增大的一\n种现象。\n生物放大系数 (biomagnification factor, BMF)\n较高营养级生物体内污染物的浓度 (mg/kg)\n较低营养级生物体内污染物的浓度 (mg/kg)\nDDT浓度被放大了一千万倍\n0milliontimses ncrease ofDDTin fish-eating bird25ppmDDTinlargefish 2ppm 大鱼\n小鱼 DDTin0.5ppmzooplankton DDTin 浮游生物\n0.04ppm0.000003ppms DDTinwater 水中",
      "ocr_lines_count": 33,
      "ocr_score": 0.963
    },
    {
      "index": 19,
      "image": "page_019.jpg",
      "embedded_text": null,
      "ocr_text": "2.3环境污染物的转化\n污染物的转化是指污染物在环境中，通过物理\n化学或生物学的作用来改变形态或者转变为一种物质的\n过程，\n一次污染物通常指由污染源直接排入环境的污染\n物，而在环境中发生各种反应从而转化形成的污染物被\n称为二次污染物。\n太阳 氧原子 污染物浓度（mL/m）\n臭氧\n氧化氮 0.4\n外线 醛类\n过氧硝\n酸乙酰 0.3\n空气中的氧 非甲烷烃\n0.2 醛\n光化学烟雾\n0.1 NO0:004:008:0012:0016:0020:00（时）\n图1 图2",
      "ocr_lines_count": 32,
      "ocr_score": 0.981
    },
    {
      "index": 20,
      "image": "page_020.jpg",
      "embedded_text": null,
      "ocr_text": "2.3环境污染物的转化\n一般地，污染物的转化过程主要取决于其本身的理\n化性质以及所处的环境条件。\n物理转化\n转化形式 化学转化\n生物转化",
      "ocr_lines_count": 9,
      "ocr_score": 0.989
    },
    {
      "index": 21,
      "image": "page_021.jpg",
      "embedded_text": null,
      "ocr_text": "2.3环境污染物的转化\n一、物理转化作用\n蒸发\n污染物的分子微观形态发生\n渗透\n了改变，其空间位置也存在变化\n凝聚 因而，通常认为污染物的物理转化\n吸附 与其迁移运动之间存在较为密切的\n伴随关系。\n放射性元素的蜕变\n二、化学转化作用\n化学转化作用指污染物通过各种化学反应过程发生\n的转化。\n水解反应\n氧化还原反应\n络合反应\n光化学反应",
      "ocr_lines_count": 21,
      "ocr_score": 0.993
    },
    {
      "index": 22,
      "image": "page_022.jpg",
      "embedded_text": null,
      "ocr_text": "2.3环境污染物的转化\n（一）大气中的化学转化\n在大气中，污染物的化学转化主要包括光化学氧化\n和催化氧化。\n美国“洛杉矶光化学烟雾事件”\n光化学氧化作用\n氮氧化物和碳氢化物 光化学烟雾\n硫酸雾\n光化学氧化作用 水，硫酸或硫酸盐\nSO2 SO3 ·酸雨酸雾\n催化氧化作用\ncard.all&vd_source=4885c3ef5914fc7de7efe1fb94dce7e7",
      "ocr_lines_count": 20,
      "ocr_score": 0.972
    },
    {
      "index": 23,
      "image": "page_023.jpg",
      "embedded_text": null,
      "ocr_text": "2.3环境污染物的转化\n羟基自由基（OH·）\n在气态污染物\n的催化氧化降解 硝酸盐自由基（NO3·)\n中起重要作用\n超氧自由基（O2·)\n大多数气态污染物在光化学反应过程中能够产生\n羟基从而发生降解。",
      "ocr_lines_count": 11,
      "ocr_score": 0.97
    },
    {
      "index": 24,
      "image": "page_024.jpg",
      "embedded_text": null,
      "ocr_text": "2.3环境污染物的转化\n（二）水体中的化学转化\n在水体中，污染物的化学转化主要以氧化还原反应和络\n合水解反应为主。\n溢入海洋水面的油膜，也会在太阳光的作用下发生光化学氧\n化，每平方千米海面每天被氧化的石油烃最高值可达2吨之多。",
      "ocr_lines_count": 8,
      "ocr_score": 0.988
    },
    {
      "index": 25,
      "image": "page_025.jpg",
      "embedded_text": null,
      "ocr_text": "2.3环境污染物的转化\n（三）土壤中的化学转化\n污染物在土壤中的转化及其行为的影响因素也非常\n多。其中土壤中固、液、气三相的分布是控制污染物运\n动和微生物活动的重要因素。\n固、液、气三相的分布\npH\n污染物转化的条件 温度\n湿度\n通气状况",
      "ocr_lines_count": 13,
      "ocr_score": 0.989
    },
    {
      "index": 26,
      "image": "page_026.jpg",
      "embedded_text": null,
      "ocr_text": "2.3环境污染物的转化\n三、生物转化和生物降解作用\n生物转化和生物降解作用是指外源污染物在机\n体内经多种酶的催化作用所发生的代谢转化过程。",
      "ocr_lines_count": 6,
      "ocr_score": 0.984
    },
    {
      "index": 27,
      "image": "page_027.jpg",
      "embedded_text": null,
      "ocr_text": "2.3环境污染物的转化\n（一） 微生物对污染物的转化和降解\nNO21.微生物降解农药的方式：\n（1）将农药作为唯一碳源和能 NO2\n源，或者作为唯一的氨源物质\n分子式：C13H18F3Ns04\n（2）共代谢作用 氟乐灵\n脱卤作用、脱烃作用，对酰胺及脂\n的水解、氧化作用、还原作用，以\n及环裂解、缩合等方式",
      "ocr_lines_count": 18,
      "ocr_score": 0.934
    },
    {
      "index": 28,
      "image": "page_028.jpg",
      "embedded_text": null,
      "ocr_text": "2.3环境污染物的转化\n2.微生物对重金属的转化和降解\n（1）可以改变重金属在环境中存在的状态，会\n使化学物毒性增强，还可以浓缩重金属，并通\n过食物链进行积累\n(2） 微生物也可以直接和间接地去除环境中的\n重金属，从而有助于改善环境",
      "ocr_lines_count": 10,
      "ocr_score": 0.976
    },
    {
      "index": 29,
      "image": "page_029.jpg",
      "embedded_text": null,
      "ocr_text": "2.3环境污染物的转化\n（二）植物对污染物的转化和降解\n挥发、蒸腾\n1.植物对污染物的转化和降解 挥发、蒸腾\n汞、硒\n沉积\n甲醛、SO2和苯等\n植物体内\n酚 酚糖贰 →二氧化碳和水 重金属\n放射性核业 根际代谢物\n植物体内 TCE/PCE\n氰化物 丝氨酸等氨基酸类物质\n代谢物\n水稻 金属、有机物\n苯并[a]芘 二氧化碳和有机酸 和放射性核素\n无机物 有机物\n2.植物根系与其根际微生物微生态系统的降解转化 重金属\n放射性核素 TCE(三氣乙烯）\nPCE（29氧乙）\n有机氯农药 +其他有机氯化物 土壤和沉积物\n稳定\n（三） 动物对污染物的转化和降解\n肝脏和肝外组织细胞中各种酶\n污染物 →转化和降解",
      "ocr_lines_count": 43,
      "ocr_score": 0.958
    },
    {
      "index": 30,
      "image": "page_030.jpg",
      "embedded_text": null,
      "ocr_text": "第二章污染物在环境中的迁移和转化\n1.各种污染物在环境中的迁移方式主要包括（）多选\nA.机械性迁移\nB．物理化学性迁移\nC.生物性迁移\nD.随机迁移",
      "ocr_lines_count": 8,
      "ocr_score": 0.982
    },
    {
      "index": 31,
      "image": "page_031.jpg",
      "embedded_text": null,
      "ocr_text": "第二章污染物在环境中的迁移和转化\n2.气的机械性迁移作用指污染物在大气中的扩散和被气流搬\n运，包括污染物在大气中的扩散作用\nB.×",
      "ocr_lines_count": 7,
      "ocr_score": 0.958
    },
    {
      "index": 32,
      "image": "page_032.jpg",
      "embedded_text": null,
      "ocr_text": "第二章污染物在环境中的迁移和转化\n3.逆温现象发生在大气中的对流层，发生后大气稳定度低\n对流作用大为减弱，污染物无法随空气运动扩散。\nB.×",
      "ocr_lines_count": 7,
      "ocr_score": 0.963
    },
    {
      "index": 33,
      "image": "page_033.jpg",
      "embedded_text": null,
      "ocr_text": "第二章污染物在环境中的迁移和转化\n4.以下那些是无机化合物的常见迁移方式（）多选\nA.吸附-解析\nB.氧化-还原\nC.络合和鳌合\nD.生化分解",
      "ocr_lines_count": 8,
      "ocr_score": 0.981
    },
    {
      "index": 34,
      "image": "page_034.jpg",
      "embedded_text": null,
      "ocr_text": "第二章污染物在环境中的迁移和转化\n5.以下属于二次污染物的是（）单选\nA.氟氧化物\nB．二氧化硫\nC.光化学烟雾\nD.一氧化碳",
      "ocr_lines_count": 8,
      "ocr_score": 0.976
    },
    {
      "index": 35,
      "image": "page_035.jpg",
      "embedded_text": null,
      "ocr_text": "第二章污染物在环境中的迁移和转化\n定义：污染物在环境中空间位置相对改变的过程\n污染物迁移概述 迁移原因：自身理化性质和环境因素共同作用\n迁移影响：改变局部环境污染物浓度、种类和综合毒性\n机械性迁移：气、水、重力的机械性迁移及人为搬运\n迁移的主要类型 物理－化学性迁移：风化淋溶、溶解挥发等六种作用\n生物性迁移：生物浓缩、积累、放大及其系数表示\n定义：通过物理、化学或生物作用改变形态或物质种类\n污染物转化概述 转化类型：物理、化学、生物转化三种类型\n转化意义：改变污染物毒性和存在形态，影响环境和生物\n物理转化作用：蒸发、渗透等过程实现转化，与迁移伴随\n转化的具体过程 化学转化作用：大气、水体、王壤中分别有不同反应\n生物转化和降解作用：微生物、植物、动物对污染物的转化降解",
      "ocr_lines_count": 19,
      "ocr_score": 0.991
    }
  ],
  "all_chapter_nums": [
    2,
    3
  ],
  "all_chapter_raws": [
    "第二章",
    "第三章"
  ]
}